stopwordz/__init__.py
stopwordz/stopwords.py
stopwordz/tests/__init__.py
stopwordz/tests/test_stopwords.py
stopwordz-0.2.dist-info/METADATA
stopwordz-0.2.dist-info/WHEEL
stopwordz-0.2.dist-info/top_level.txt
stopwordz-0.2.dist-info/RECORD
