Metadata-Version: 2.1
Name: stopwordz
Version: 0.2
Summary: A simple stopword cleaner
Home-page: https://github.com/subaashnair/stopwordz
Author: Subashanan Nair
Author-email: subaashnair12@gmail.com
Classifier: Development Status :: 3 - Alpha
Classifier: Intended Audience :: Developers
Classifier: Programming Language :: Python :: 3
Classifier: Programming Language :: Python :: 3.7
Classifier: Programming Language :: Python :: 3.8
Classifier: Programming Language :: Python :: 3.9
